{"bounds":"[44,66][1036,1291]","boundsRatio":{"height":0.5518018018018018,"width":0.9185185185185185,"top":0.02972972972972973,"left":0.040740740740740744},"children":[{"bounds":"[44,66][1036,1291]","boundsRatio":{"height":0.5518018018018018,"width":0.9185185185185185,"top":0.02972972972972973,"left":0.040740740740740744},"children":[{"bounds":"[44,66][1036,1291]","boundsRatio":{"height":0.5518018018018018,"width":0.9185185185185185,"top":0.02972972972972973,"left":0.040740740740740744},"children":[{"bounds":"[44,66][1036,165]","boundsRatio":{"height":0.0445945945945946,"width":0.9185185185185185,"top":0.02972972972972973,"left":0.040740740740740744},"children":[],"className":"android.widget.TextView","contentDesc":"","hintText":"","inheritedLabel":"","isAccessibilityFocused":false,"isCheckable":false,"isChecked":false,"isClickable":true,"isContentInvalid":false,"isContextClickable":false,"isDismissable":false,"isEditable":false,"isEnabled":true,"isFocusable":false,"isFocused":false,"isImportantForAccessibility":true,"isLongClickable":false,"isMultiLine":true,"isPassword":false,"isScreenReaderFocusable":false,"isScrollable":false,"isSelected":false,"isShowingHintText":false,"isVisibleToUser":true,"packageName":"com.grubhub.android","paneTitle":"","rect":{"bottom":165,"left":44,"right":1036,"top":66},"resourceId":"com.grubhub.android:id/address_info_spinner_value","screenHeight":2220,"screenWidth":1080,"text":"Alabama","tooltipText":""},{"bounds":"[44,165][1036,264]","boundsRatio":{"height":0.0445945945945946,"width":0.9185185185185185,"top":0.07432432432432433,"left":0.040740740740740744},"children":[],"className":"android.widget.TextView","contentDesc":"","hintText":"","inheritedLabel":"","isAccessibilityFocused":false,"isCheckable":false,"isChecked":false,"isClickable":true,"isContentInvalid":false,"isContextClickable":false,"isDismissable":false,"isEditable":false,"isEnabled":true,"isFocusable":false,"isFocused":false,"isImportantForAccessibility":true,"isLongClickable":false,"isMultiLine":true,"isPassword":false,"isScreenReaderFocusable":false,"isScrollable":false,"isSelected":false,"isShowingHintText":false,"isVisibleToUser":true,"packageName":"com.grubhub.android","paneTitle":"","rect":{"bottom":264,"left":44,"right":1036,"top":165},"resourceId":"com.grubhub.android:id/address_info_spinner_value","screenHeight":2220,"screenWidth":1080,"text":"Alaska","tooltipText":""},{"bounds":"[44,264][1036,363]","boundsRatio":{"height":0.0445945945945946,"width":0.9185185185185185,"top":0.11891891891891893,"left":0.040740740740740744},"children":[],"className":"android.widget.TextView","contentDesc":"","hintText":"","inheritedLabel":"","isAccessibilityFocused":false,"isCheckable":false,"isChecked":false,"isClickable":true,"isContentInvalid":false,"isContextClickable":false,"isDismissable":false,"isEditable":false,"isEnabled":true,"isFocusable":false,"isFocused":false,"isImportantForAccessibility":true,"isLongClickable":false,"isMultiLine":true,"isPassword":false,"isScreenReaderFocusable":false,"isScrollable":false,"isSelected":false,"isShowingHintText":false,"isVisibleToUser":true,"packageName":"com.grubhub.android","paneTitle":"","rect":{"bottom":363,"left":44,"right":1036,"top":264},"resourceId":"com.grubhub.android:id/address_info_spinner_value","screenHeight":2220,"screenWidth":1080,"text":"Arizona","tooltipText":""},{"bounds":"[44,363][1036,462]","boundsRatio":{"height":0.0445945945945946,"width":0.9185185185185185,"top":0.1635135135135135,"left":0.040740740740740744},"children":[],"className":"android.widget.TextView","contentDesc":"","hintText":"","inheritedLabel":"","isAccessibilityFocused":false,"isCheckable":false,"isChecked":false,"isClickable":true,"isContentInvalid":false,"isContextClickable":false,"isDismissable":false,"isEditable":false,"isEnabled":true,"isFocusable":false,"isFocused":false,"isImportantForAccessibility":true,"isLongClickable":false,"isMultiLine":true,"isPassword":false,"isScreenReaderFocusable":false,"isScrollable":false,"isSelected":false,"isShowingHintText":false,"isVisibleToUser":true,"packageName":"com.grubhub.android","paneTitle":"","rect":{"bottom":462,"left":44,"right":1036,"top":363},"resourceId":"com.grubhub.android:id/address_info_spinner_value","screenHeight":2220,"screenWidth":1080,"text":"Arkansas","tooltipText":""},{"bounds":"[44,462][1036,561]","boundsRatio":{"height":0.0445945945945946,"width":0.9185185185185185,"top":0.20810810810810812,"left":0.040740740740740744},"children":[],"className":"android.widget.TextView","contentDesc":"","hintText":"","inheritedLabel":"","isAccessibilityFocused":false,"isCheckable":false,"isChecked":false,"isClickable":true,"isContentInvalid":false,"isContextClickable":false,"isDismissable":false,"isEditable":false,"isEnabled":true,"isFocusable":false,"isFocused":false,"isImportantForAccessibility":true,"isLongClickable":false,"isMultiLine":true,"isPassword":false,"isScreenReaderFocusable":false,"isScrollable":false,"isSelected":false,"isShowingHintText":false,"isVisibleToUser":true,"packageName":"com.grubhub.android","paneTitle":"","rect":{"bottom":561,"left":44,"right":1036,"top":462},"resourceId":"com.grubhub.android:id/address_info_spinner_value","screenHeight":2220,"screenWidth":1080,"text":"California","tooltipText":""},{"bounds":"[44,561][1036,660]","boundsRatio":{"height":0.0445945945945946,"width":0.9185185185185185,"top":0.2527027027027027,"left":0.040740740740740744},"children":[],"className":"android.widget.TextView","contentDesc":"","hintText":"","inheritedLabel":"","isAccessibilityFocused":false,"isCheckable":false,"isChecked":false,"isClickable":true,"isContentInvalid":false,"isContextClickable":false,"isDismissable":false,"isEditable":false,"isEnabled":true,"isFocusable":false,"isFocused":false,"isImportantForAccessibility":true,"isLongClickable":false,"isMultiLine":true,"isPassword":false,"isScreenReaderFocusable":false,"isScrollable":false,"isSelected":false,"isShowingHintText":false,"isVisibleToUser":true,"packageName":"com.grubhub.android","paneTitle":"","rect":{"bottom":660,"left":44,"right":1036,"top":561},"resourceId":"com.grubhub.android:id/address_info_spinner_value","screenHeight":2220,"screenWidth":1080,"text":"Colorado","tooltipText":""},{"bounds":"[44,660][1036,759]","boundsRatio":{"height":0.0445945945945946,"width":0.9185185185185185,"top":0.2972972972972973,"left":0.040740740740740744},"children":[],"className":"android.widget.TextView","contentDesc":"","hintText":"","inheritedLabel":"","isAccessibilityFocused":false,"isCheckable":false,"isChecked":false,"isClickable":true,"isContentInvalid":false,"isContextClickable":false,"isDismissable":false,"isEditable":false,"isEnabled":true,"isFocusable":false,"isFocused":false,"isImportantForAccessibility":true,"isLongClickable":false,"isMultiLine":true,"isPassword":false,"isScreenReaderFocusable":false,"isScrollable":false,"isSelected":false,"isShowingHintText":false,"isVisibleToUser":true,"packageName":"com.grubhub.android","paneTitle":"","rect":{"bottom":759,"left":44,"right":1036,"top":660},"resourceId":"com.grubhub.android:id/address_info_spinner_value","screenHeight":2220,"screenWidth":1080,"text":"Connecticut","tooltipText":""},{"bounds":"[44,759][1036,858]","boundsRatio":{"height":0.0445945945945946,"width":0.9185185185185185,"top":0.3418918918918919,"left":0.040740740740740744},"children":[],"className":"android.widget.TextView","contentDesc":"","hintText":"","inheritedLabel":"","isAccessibilityFocused":false,"isCheckable":false,"isChecked":false,"isClickable":true,"isContentInvalid":false,"isContextClickable":false,"isDismissable":false,"isEditable":false,"isEnabled":true,"isFocusable":false,"isFocused":false,"isImportantForAccessibility":true,"isLongClickable":false,"isMultiLine":true,"isPassword":false,"isScreenReaderFocusable":false,"isScrollable":false,"isSelected":false,"isShowingHintText":false,"isVisibleToUser":true,"packageName":"com.grubhub.android","paneTitle":"","rect":{"bottom":858,"left":44,"right":1036,"top":759},"resourceId":"com.grubhub.android:id/address_info_spinner_value","screenHeight":2220,"screenWidth":1080,"text":"District of Columbia","tooltipText":""},{"bounds":"[44,858][1036,957]","boundsRatio":{"height":0.0445945945945946,"width":0.9185185185185185,"top":0.3864864864864865,"left":0.040740740740740744},"children":[],"className":"android.widget.TextView","contentDesc":"","hintText":"","inheritedLabel":"","isAccessibilityFocused":false,"isCheckable":false,"isChecked":false,"isClickable":true,"isContentInvalid":false,"isContextClickable":false,"isDismissable":false,"isEditable":false,"isEnabled":true,"isFocusable":false,"isFocused":false,"isImportantForAccessibility":true,"isLongClickable":false,"isMultiLine":true,"isPassword":false,"isScreenReaderFocusable":false,"isScrollable":false,"isSelected":false,"isShowingHintText":false,"isVisibleToUser":true,"packageName":"com.grubhub.android","paneTitle":"","rect":{"bottom":957,"left":44,"right":1036,"top":858},"resourceId":"com.grubhub.android:id/address_info_spinner_value","screenHeight":2220,"screenWidth":1080,"text":"Delaware","tooltipText":""},{"bounds":"[44,957][1036,1056]","boundsRatio":{"height":0.0445945945945946,"width":0.9185185185185185,"top":0.43108108108108106,"left":0.040740740740740744},"children":[],"className":"android.widget.TextView","contentDesc":"","hintText":"","inheritedLabel":"","isAccessibilityFocused":false,"isCheckable":false,"isChecked":false,"isClickable":true,"isContentInvalid":false,"isContextClickable":false,"isDismissable":false,"isEditable":false,"isEnabled":true,"isFocusable":false,"isFocused":false,"isImportantForAccessibility":true,"isLongClickable":false,"isMultiLine":true,"isPassword":false,"isScreenReaderFocusable":false,"isScrollable":false,"isSelected":false,"isShowingHintText":false,"isVisibleToUser":true,"packageName":"com.grubhub.android","paneTitle":"","rect":{"bottom":1056,"left":44,"right":1036,"top":957},"resourceId":"com.grubhub.android:id/address_info_spinner_value","screenHeight":2220,"screenWidth":1080,"text":"Florida","tooltipText":""},{"bounds":"[44,1056][1036,1155]","boundsRatio":{"height":0.0445945945945946,"width":0.9185185185185185,"top":0.4756756756756757,"left":0.040740740740740744},"children":[],"className":"android.widget.TextView","contentDesc":"","hintText":"","inheritedLabel":"","isAccessibilityFocused":false,"isCheckable":false,"isChecked":false,"isClickable":true,"isContentInvalid":false,"isContextClickable":false,"isDismissable":false,"isEditable":false,"isEnabled":true,"isFocusable":false,"isFocused":false,"isImportantForAccessibility":true,"isLongClickable":false,"isMultiLine":true,"isPassword":false,"isScreenReaderFocusable":false,"isScrollable":false,"isSelected":false,"isShowingHintText":false,"isVisibleToUser":true,"packageName":"com.grubhub.android","paneTitle":"","rect":{"bottom":1155,"left":44,"right":1036,"top":1056},"resourceId":"com.grubhub.android:id/address_info_spinner_value","screenHeight":2220,"screenWidth":1080,"text":"Georgia","tooltipText":""},{"bounds":"[44,1155][1036,1254]","boundsRatio":{"height":0.0445945945945946,"width":0.9185185185185185,"top":0.5202702702702703,"left":0.040740740740740744},"children":[],"className":"android.widget.TextView","contentDesc":"","hintText":"","inheritedLabel":"","isAccessibilityFocused":false,"isCheckable":false,"isChecked":false,"isClickable":true,"isContentInvalid":false,"isContextClickable":false,"isDismissable":false,"isEditable":false,"isEnabled":true,"isFocusable":false,"isFocused":false,"isImportantForAccessibility":true,"isLongClickable":false,"isMultiLine":true,"isPassword":false,"isScreenReaderFocusable":false,"isScrollable":false,"isSelected":false,"isShowingHintText":false,"isVisibleToUser":true,"packageName":"com.grubhub.android","paneTitle":"","rect":{"bottom":1254,"left":44,"right":1036,"top":1155},"resourceId":"com.grubhub.android:id/address_info_spinner_value","screenHeight":2220,"screenWidth":1080,"text":"Hawaii","tooltipText":""},{"bounds":"[44,1254][1036,1291]","boundsRatio":{"height":0.016666666666666666,"width":0.9185185185185185,"top":0.5648648648648649,"left":0.040740740740740744},"children":[],"className":"android.widget.TextView","contentDesc":"","hintText":"","inheritedLabel":"","isAccessibilityFocused":false,"isCheckable":false,"isChecked":false,"isClickable":true,"isContentInvalid":false,"isContextClickable":false,"isDismissable":false,"isEditable":false,"isEnabled":true,"isFocusable":false,"isFocused":false,"isImportantForAccessibility":true,"isLongClickable":false,"isMultiLine":true,"isPassword":false,"isScreenReaderFocusable":false,"isScrollable":false,"isSelected":false,"isShowingHintText":false,"isVisibleToUser":false,"packageName":"com.grubhub.android","paneTitle":"","rect":{"bottom":1291,"left":44,"right":1036,"top":1254},"resourceId":"com.grubhub.android:id/address_info_spinner_value","screenHeight":2220,"screenWidth":1080,"text":"Idaho","tooltipText":""}],"className":"android.widget.ListView","contentDesc":"","hintText":"","inheritedLabel":"","isAccessibilityFocused":false,"isCheckable":false,"isChecked":false,"isClickable":false,"isContentInvalid":false,"isContextClickable":false,"isDismissable":false,"isEditable":false,"isEnabled":true,"isFocusable":true,"isFocused":false,"isImportantForAccessibility":true,"isLongClickable":false,"isMultiLine":false,"isPassword":false,"isScreenReaderFocusable":false,"isScrollable":true,"isSelected":false,"isShowingHintText":false,"isVisibleToUser":true,"packageName":"com.grubhub.android","paneTitle":"","rect":{"bottom":1291,"left":44,"right":1036,"top":66},"resourceId":"","screenHeight":2220,"screenWidth":1080,"text":"","tooltipText":""}],"className":"android.widget.FrameLayout","contentDesc":"","hintText":"","inheritedLabel":"","isAccessibilityFocused":false,"isCheckable":false,"isChecked":false,"isClickable":false,"isContentInvalid":false,"isContextClickable":false,"isDismissable":false,"isEditable":false,"isEnabled":true,"isFocusable":false,"isFocused":false,"isImportantForAccessibility":false,"isLongClickable":false,"isMultiLine":false,"isPassword":false,"isScreenReaderFocusable":false,"isScrollable":false,"isSelected":false,"isShowingHintText":false,"isVisibleToUser":true,"packageName":"com.grubhub.android","paneTitle":"","rect":{"bottom":1291,"left":44,"right":1036,"top":66},"resourceId":"","screenHeight":2220,"screenWidth":1080,"text":"","tooltipText":""}],"className":"android.widget.FrameLayout","contentDesc":"","hintText":"","inheritedLabel":"","isAccessibilityFocused":false,"isCheckable":false,"isChecked":false,"isClickable":false,"isContentInvalid":false,"isContextClickable":false,"isDismissable":false,"isEditable":false,"isEnabled":true,"isFocusable":false,"isFocused":false,"isImportantForAccessibility":true,"isLongClickable":false,"isMultiLine":false,"isPassword":false,"isScreenReaderFocusable":false,"isScrollable":false,"isSelected":false,"isShowingHintText":false,"isVisibleToUser":true,"packageName":"com.grubhub.android","paneTitle":"","rect":{"bottom":1291,"left":44,"right":1036,"top":66},"resourceId":"","screenHeight":2220,"screenWidth":1080,"text":"","tooltipText":""}